<?xml version="1.0" encoding="utf-8"?>
<odoo>

    <record model="ir.ui.view" id="inherit_department">
        <field name="name">hr.department.formt</field>
        <field name="model">hr.department</field>
        <field name="inherit_id" ref="hr.view_department_form"/>
        <field name="arch" type="xml">
            <xpath expr="//group[1]" position="after">
                <group string="Attendance Information">
                    <field name="st_checkin" placeholder="00:00"/>
                    <field name="st_checkout" placeholder="00:00"/>
                    <field name="grace_time" placeholder="00:00"/>
                </group>
            </xpath>
        </field>
    </record>
    <record model="ir.ui.view" id="inherit_employee">
        <field name="name">hr.employee.formt</field>
        <field name="model">hr.employee</field>
        <field name="inherit_id" ref="hr.view_employee_form"/>
        <field name="arch" type="xml">
            <xpath expr="//field[@name='tz']" position="after">
                <group string="Attendance Information">
                    <field name="st_checkin" placeholder="00:00"/>
                    <field name="st_checkout" placeholder="00:00"/>
                    <field name="grace_time" placeholder="00:00"/>
                </group>
            </xpath>
        </field>
    </record>

    <record id="action_attendance" model="ir.actions.act_window">
        <field name="name">Attendance</field>
        <field name="type">ir.actions.act_window</field>
        <field name="res_model">attendance.custom</field>
        <field name="view_mode">tree,kanban,form</field>

    </record>
    <record id="view_attendance_ing_tree" model="ir.ui.view">
        <field name="name">custom.attendance.tree</field>
        <field name="model">attendance.custom</field>
        <field name="arch" type="xml">
            <tree string="Attendance list">
                <field name="roll_number"/>
                <field name="employee_id"/>

                <field name="job_title"/>
                <field name="attendance_date"/>
                <field name="first_check_in"/>
                <field name="first_check_out"/>

                <field name="second_check_in"/>
                <field name="second_check_out"/>

                <field name="ot_15"/>
                <field name="ot_125"/>
                <field name="working"/>
                <field name="absent"/>


            </tree>
        </field>
    </record>

    <record model="ir.ui.view" id="action_form">
        <field name="name">attendance.custom.form</field>
        <field name="model">attendance.custom</field>
        <field name="arch" type="xml">
            <form class="o_lead_opportunity_form">

                <sheet>
                    <separator style="color:black;font-weight:bold;font-size:28px;" string="Attendance Information"
                               colspan="4"/>
                    <group col="4" colspan="12">
                        <field name="employee_id"/>
                        <field name="attendance_date"/>
                        <field name="roll_number"/>
                        <field name="custom_ID"/>
                        <field name="job_title"/>
                        <field name="job_code"/>
                        <field name="site"/>
                        <field name="status"/>
                    </group>

                    <group col="2" string="First Shift" colspan="12">
                        <field name="first_check_in" placeholder="00:00"/>
                        <field name="first_check_out" placeholder="00:00"/>
                        <field name="first_shift_total_hours" placeholder="00:00"/>
                    </group>
                    <group col="2" string="Second Shift" colspan="12">
                        <field name="second_check_in" placeholder="00:00"/>
                        <field name="second_check_out" placeholder="00:00"/>
                        <field name="second_shift_total_hours" placeholder="00:00"/>
                    </group>

                    <group col="4" colspan="12">
                        <field name="working" placeholder="00:00"/>
                        <field name="late_in" placeholder="00:00"/>
                        <field name="apply_latein_deduction" force_save="1"/>
                        <field name="exception_approved"/>
                        <field name="early_in" placeholder="00:00"/>
                        <field name="early_out" placeholder="00:00"/>
                        <field name="ot_15" placeholder="00:00"/>
                        <field name="ot_125" placeholder="00:00"/>
                        <field name="no_attend" placeholder="00:00"/>
                        <field name="ignored" placeholder="00:00"/>
                    </group>

                    <group col="2" colspan="8">
                        <field name="absent"/>

                        <field name="sick_leave"/>

                        <field name="sick_from"
                               attrs="{'required':[('sick_leave','=',True)],'invisible':[('sick_leave','!=',True)]}"/>
                        <field name="sick_to"
                               attrs="{'required':[('sick_leave','=',True)],'invisible':[('sick_leave','!=',True)]}"/>

                    </group>

                </sheet>
            </form>
        </field>
    </record>


    <menuitem id="menu_attendence" name="Attendance"
              web_icon="attendance_customization,static/description/icon.png"
              sequence="12"/>
    <menuitem name="Attendance" id="ums_attendence_root"
              parent="menu_attendence"
              sequence="2" action="action_attendance"/>


</odoo>
